{
  "index": 2,
  "1": {
          "a": "m x g x h",
          "b": "m / g x h",
          "c": "s x v x h",
          "d": "x / h x b",
          "q": "What is the equation to calculate gravitational potential energy?"
       },
  "2": {
         "a": "1/2 x m x v squared",
         "b": "3/4 x m x the square root of v",
         "c": "1/8 x g x f",
         "d": "4/5 x n x m",
         "q": "What is the equation to calculate kinetic energy?"
  },
  
  "3": {
    "a": "m x v",
    "b": "m / v",
    "c": "m x v squared",
    "d": "m / v squard",
    "q": "How do you calculate momentum?
  }
  
  }
